Fraunhofer-1.0.3.data/scripts/hofer
fraunhofer/__init__.py
fraunhofer/kurucz.py
fraunhofer/marcs.py
fraunhofer/models.py
fraunhofer/specfit.py
fraunhofer/specfit_mod.py
fraunhofer/data/am05ak2odfnew.dat
fraunhofer/data/am05k2odfnew.dat
fraunhofer/data/am10ak2odfnew.dat
fraunhofer/data/am10k2odfnew.dat
fraunhofer/data/am15ak2odfnew.dat
fraunhofer/data/am15k2odfnew.dat
fraunhofer/data/am20ak2odfnew.dat
fraunhofer/data/am20k2odfnew.dat
fraunhofer/data/am25ak2odfnew.dat
fraunhofer/data/am25k2odfnew.dat
fraunhofer/data/am40ak2odfnew.dat
fraunhofer/data/ap00ak2odfnew.dat
fraunhofer/data/ap00k2odfnew.dat
fraunhofer/data/ap05ak2odfnew.dat
fraunhofer/data/ap05k2odfnew.dat
fraunhofer/data/asun.dat
fraunhofer/data/avega.dat
fraunhofer/data/marcs_data.pkl
fraunhofer/data/marcs_index.fits
fraunhofer/data/periodic_table.txt
fraunhofer/data/tefflogg.txt
Fraunhofer-1.0.3.dist-info/LICENSE
Fraunhofer-1.0.3.dist-info/METADATA
Fraunhofer-1.0.3.dist-info/WHEEL
Fraunhofer-1.0.3.dist-info/top_level.txt
Fraunhofer-1.0.3.dist-info/RECORD
